zrouter/__init__.py
zrouter/restful.py
zrouter/router.py
zrouter/decorators/__init__.py
zrouter/exceptions/__init__.py
zrouter/utils/log.py
zrouter/utils/memory.py
zrouter/utils/session.py
zrouter/utils/base/json.py
zrouter/utils/database/__init__.py
zrouter-0.6.7.dist-info/METADATA
zrouter-0.6.7.dist-info/WHEEL
zrouter-0.6.7.dist-info/licenses/LICENSE
zrouter-0.6.7.dist-info/RECORD
