Metadata-Version: 2.1
Name: zrouter
Version: 0.6.7
Summary: zen router library
Project-URL: Homepage, https://github.com/inspirare6/zrouter
Project-URL: Bug Tracker, https://github.com/inspirare6/zrouter/issues
Author-email: inspirare6 <inspirare6@163.com>
License-File: LICENSE
Classifier: License :: OSI Approved :: MIT License
Classifier: Operating System :: OS Independent
Classifier: Programming Language :: Python :: 3
Requires-Python: >=3.7
Requires-Dist: flask==2.2.2
Requires-Dist: jsonschema==4.17.3
Requires-Dist: zmemory==0.1.3
